setup.py
aws_auth_helper.egg-info/PKG-INFO
aws_auth_helper.egg-info/SOURCES.txt
aws_auth_helper.egg-info/dependency_links.txt
aws_auth_helper.egg-info/requires.txt
aws_auth_helper.egg-info/top_level.txt
awsauthhelper/__init__.py
awsauthhelper/password.py
tests/__init__.py
tests/test_credentials.py
tests/test_enforced_auth_type.py
tests/test_envDefault.py
tests/test_password.py
tests/test_testhelper.py
tests/test_validate_creds.py