Metadata-Version: 1.1
Name: aws-auth-helper
Version: 1.5.0
Summary: Helper library providing ArgumentParser and Credentials class for AWS authentication
Home-page: http://aws-auth-helper.readthedocs.org/
Author: Drew J. Sonne
Author-email: drew.sonne@gmail.com
License: GPLv2
Download-URL: https://github.com/drewsonne/awsauthhelper/archive/v.1.5.0.tar.gz
Platform: UNKNOWN
Classifier: Development Status :: 5 - Production/Stable
Classifier: Intended Audience :: Developers
Classifier: Intended Audience :: Information Technology
Classifier: License :: OSI Approved :: GNU General Public License v2 (GPLv2)
Classifier: Natural Language :: English
Classifier: Operating System :: MacOS :: MacOS X
Classifier: Operating System :: POSIX :: Linux
Classifier: Programming Language :: Python :: 2.7
Classifier: Topic :: Software Development :: Libraries
Classifier: Topic :: Software Development :: Libraries :: Python Modules
Classifier: Topic :: System :: Systems Administration :: Authentication/Directory
